Workbook

Sheet 0 – Executive Summary
A2: Top Client | B2: =_xlfn.XLOOKUP(1,'I – Client Intelligence'!I3:I22,'I – Client Intelligence'!A3:A22) -> Comte de Paris
A3: Top Client Spend (fr) | B3: =_xlfn.XLOOKUP(1,'I – Client Intelligence'!I3:I22,'I – Client Intelligence'!E3:E22) -> 5500
A4: Top Client % of Revenue | B4: =_xlfn.XLOOKUP(1,'I – Client Intelligence'!I3:I22,'I – Client Intelligence'!G3:G22) -> 17.74
A5: Top Craftsman | B5: =_xlfn.XLOOKUP(MAX('II – Craftsman Output'!E3:E11),'II – Craftsman Output'!E3:E11,'II – Craftsman Output'!A3:A11) -> Thierry Hermes
A6: Top Craftsman Revenue (fr) | B6: =_xlfn.XLOOKUP(MAX('II – Craftsman Output'!E3:E11),'II – Craftsman Output'!E3:E11,'II – Craftsman Output'!E3:E11) -> 14810
A7: Highest Margin Product | B7: =_xlfn.XLOOKUP(MAX('III – Margin Analysis'!F3:F17),'III – Margin Analysis'!F3:F17,'III – Margin Analysis'!A3:A17) -> Carved Dispatch Satchel
A8: Highest Margin % | B8: =_xlfn.XLOOKUP(MAX('III – Margin Analysis'!F3:F17),'III – Margin Analysis'!F3:F17,'III – Margin Analysis'!F3:F17) -> 91.28
A9: Total Atelier Revenue (fr) | B9: =SUM('II – Craftsman Output'!E3:E11) -> 31005
A10: Peak Revenue Year | B10: =_xlfn.XLOOKUP(MAX('IV – Revenue & Growth'!C3:C31),'IV – Revenue & Growth'!C3:C31,'IV – Revenue & Growth'!A3:A31) -> 1862

Sheet I – Client Intelligence
A2: Client Name | B2: Client Tier | C2: Country | D2: Total Orders | E2: Total Sales (fr) | F2: Avg Order (fr) | G2: % of Revenue | H2: Tier Rank | I2: Spend Rank
A3: Comte de Paris | B3: Royalty | C3: France | D3: 2 | E3: 5500 | F3: =ROUND(E3/D3,2) -> 2750 | G3: =ROUND((E3/SUM($E$3:$E$22))*100,2) -> 17.74 | H3: =COUNTIFS($B$3:$B$22,B3,$E$3:$E$22,">"&E3)+1 -> 1 | I3: =COUNTIF($E$3:$E$22,">"&E3)+1 -> 1
A4: Archduke Franz Karl | B4: Royalty | C4: Austria | D4: 2 | E4: 3720 | F4: =ROUND(E4/D4,2) -> 1860 | G4: =ROUND((E4/SUM($E$3:$E$22))*100,2) -> 12 | H4: =COUNTIFS($B$3:$B$22,B4,$E$3:$E$22,">"&E4)+1 -> 2 | I4: =COUNTIF($E$3:$E$22,">"&E4)+1 -> 2
A5: Prince Anatole Demidoff | B5: Royalty | C5: Russia | D5: 2 | E5: 3600 | F5: =ROUND(E5/D5,2) -> 1800 | G5: =ROUND((E5/SUM($E$3:$E$22))*100,2) -> 11.61 | H5: =COUNTIFS($B$3:$B$22,B5,$E$3:$E$22,">"&E5)+1 -> 3 | I5: =COUNTIF($E$3:$E$22,">"&E5)+1 -> 3
A6: Prince Napoleon Joseph | B6: Royalty | C6: France | D6: 2 | E6: 2770 | F6: =ROUND(E6/D6,2) -> 1385 | G6: =ROUND((E6/SUM($E$3:$E$22))*100,2) -> 8.93 | H6: =COUNTIFS($B$3:$B$22,B6,$E$3:$E$22,">"&E6)+1 -> 4 | I6: =COUNTIF($E$3:$E$22,">"&E6)+1 -> 4
A7: Marquis de Gallifet | B7: Nobility | C7: France | D7: 2 | E7: 1880 | F7: =ROUND(E7/D7,2) -> 940 | G7: =ROUND((E7/SUM($E$3:$E$22))*100,2) -> 6.06 | H7: =COUNTIFS($B$3:$B$22,B7,$E$3:$E$22,">"&E7)+1 -> 1 | I7: =COUNTIF($E$3:$E$22,">"&E7)+1 -> 5
A8: Duc de Morny | B8: Nobility | C8: France | D8: 2 | E8: 1820 | F8: =ROUND(E8/D8,2) -> 910 | G8: =ROUND((E8/SUM($E$3:$E$22))*100,2) -> 5.87 | H8: =COUNTIFS($B$3:$B$22,B8,$E$3:$E$22,">"&E8)+1 -> 2 | I8: =COUNTIF($E$3:$E$22,">"&E8)+1 -> 6
A9: General Otto von Bismarck | B9: Military | C9: Prussia | D9: 2 | E9: 1780 | F9: =ROUND(E9/D9,2) -> 890 | G9: =ROUND((E9/SUM($E$3:$E$22))*100,2) -> 5.74 | H9: =COUNTIFS($B$3:$B$22,B9,$E$3:$E$22,">"&E9)+1 -> 1 | I9: =COUNTIF($E$3:$E$22,">"&E9)+1 -> 7
A10: Prince Georges Stirbey | B10: Royalty | C10: Romania | D10: 1 | E10: 1780 | F10: =ROUND(E10/D10,2) -> 1780 | G10: =ROUND((E10/SUM($E$3:$E$22))*100,2) -> 5.74 | H10: =COUNTIFS($B$3:$B$22,B10,$E$3:$E$22,">"&E10)+1 -> 5 | I10: =COUNTIF($E$3:$E$22,">"&E10)+1 -> 7
A11: Comte de Montesquieu | B11: Nobility | C11: France | D11: 2 | E11: 1300 | F11: =ROUND(E11/D11,2) -> 650 | G11: =ROUND((E11/SUM($E$3:$E$22))*100,2) -> 4.19 | H11: =COUNTIFS($B$3:$B$22,B11,$E$3:$E$22,">"&E11)+1 -> 3 | I11: =COUNTIF($E$3:$E$22,">"&E11)+1 -> 9
A12: Lord Ashburton | B12: Nobility | C12: United Kingdom | D12: 2 | E12: 1130 | F12: =ROUND(E12/D12,2) -> 565 | G12: =ROUND((E12/SUM($E$3:$E$22))*100,2) -> 3.64 | H12: =COUNTIFS($B$3:$B$22,B12,$E$3:$E$22,">"&E12)+1 -> 4 | I12: =COUNTIF($E$3:$E$22,">"&E12)+1 -> 10
A13: Baron de Zuloaga | B13: Nobility | C13: Spain | D13: 1 | E13: 1100 | F13: =ROUND(E13/D13,2) -> 1100 | G13: =ROUND((E13/SUM($E$3:$E$22))*100,2) -> 3.55 | H13: =COUNTIFS($B$3:$B$22,B13,$E$3:$E$22,">"&E13)+1 -> 5 | I13: =COUNTIF($E$3:$E$22,">"&E13)+1 -> 11
A14: Baron von Rothschild | B14: Nobility | C14: Prussia | D14: 2 | E14: 780 | F14: =ROUND(E14/D14,2) -> 390 | G14: =ROUND((E14/SUM($E$3:$E$22))*100,2) -> 2.52 | H14: =COUNTIFS($B$3:$B$22,B14,$E$3:$E$22,">"&E14)+1 -> 6 | I14: =COUNTIF($E$3:$E$22,">"&E14)+1 -> 12
... A22: Colonel James Pemberton | B22: Military | C22: United Kingdom | D22: 1 | E22: 720 | F22: =ROUND(E22/D22,2) -> 720 | G22: =ROUND((E22/SUM($E$3:$E$22))*100,2) -> 2.32 | H22: =COUNTIFS($B$3:$B$22,B22,$E$3:$E$22,">"&E22)+1 -> 2 | I22: =COUNTIF($E$3:$E$22,">"&E22)+1 -> 13

Sheet II – Craftsman Output
A2: Craftsman | B2: Specialty | C2: Joined Year | D2: Total Orders | E2: Total Revenue (fr) | F2: Total Labour Days | G2: Revenue/Day (fr) | H2: % of Atelier Revenue
A3: Thierry Hermes | B3: Master Saddler & Harness Maker | C3: 1837 | D3: 8 | E3: 14810 | F3: 243 | G3: =ROUND(E3/F3,2) -> 60.95 | H3: =ROUND((E3/SUM($E$3:$E$11))*100,2) -> 47.77
A4: Henri Beaumont | B4: Gilding & Metal Fittings | C4: 1848 | D4: 3 | E4: 4320 | F4: 62 | G4: =ROUND(E4/F4,2) -> 69.68 | H4: =ROUND((E4/SUM($E$3:$E$11))*100,2) -> 13.93
A5: Charles Dupont | B5: Bridle & Bit Specialist | C5: 1838 | D5: 4 | E5: 2690 | F5: 60 | G5: =ROUND(E5/F5,2) -> 44.83 | H5: =ROUND((E5/SUM($E$3:$E$11))*100,2) -> 8.68
A6: Auguste Renard | B6: Leather Carving & Tooling | C6: 1840 | D6: 4 | E6: 2370 | F6: 51 | G6: =ROUND(E6/F6,2) -> 46.47 | H6: =ROUND((E6/SUM($E$3:$E$11))*100,2) -> 7.64
A7: Joseph Mercier | B7: Stitching & Assembly | C7: 1842 | D7: 4 | E7: 2310 | F7: 60 | G7: =ROUND(E7/F7,2) -> 38.5 | H7: =ROUND((E7/SUM($E$3:$E$11))*100,2) -> 7.45
A8: Pierre Delacroix | B8: Pattern Making & Cutting | C8: 1851 | D8: 2 | E8: 1560 | F8: 39 | G8: =ROUND(E8/F8,2) -> 40 | H8: =ROUND((E8/SUM($E$3:$E$11))*100,2) -> 5.03
A9: Gustave Morel | B9: Bridle & Collar Work | C9: 1857 | D9: 1 | E9: 1400 | F9: 20 | G9: =ROUND(E9/F9,2) -> 70 | H9: =ROUND((E9/SUM($E$3:$E$11))*100,2) -> 4.52
A10: Emile Fontaine | B10: Trunk & Travel Goods | C10: 1845 | D10: 3 | E10: 1185 | F10: 28 | G10: =ROUND(E10/F10,2) -> 42.32 | H10: =ROUND((E10/SUM($E$3:$E$11))*100,2) -> 3.82
A11: Francois Lamarre | B11: Harness Painting & Lacquer | C11: 1854 | D11: 1 | E11: 360 | F11: 9 | G11: =ROUND(E11/F11,2) -> 40 | H11: =ROUND((E11/SUM($E$3:$E$11))*100,2) -> 1.16

Sheet III – Margin Analysis
A2: Product Type | B2: Total Orders | C2: Avg Sale Price (fr) | D2: Avg Material Cost (fr) | E2: Avg Gross Margin (fr) | F2: Avg Margin % | G2: Margin Tier | H2: Margin Rank
A3: Carved Dispatch Satchel | B3: 1 | C3: 430 | D3: 37.5 | E3: =ROUND(C3-D3,2) -> 392.5 | F3: =ROUND((E3/C3)*100,2) -> 91.28 | G3: {=_xlfn.IFS(F3>=90,"Premium",F3>=85,"Strong",F3<85,"Standard")} -> Premium | H3: =RANK(F3,$F$3:$F$17,0) -> 1
A4: Presentation Bridle | B4: 1 | C4: 540 | D4: 47.25 | E4: =ROUND(C4-D4,2) -> 492.75 | F4: =ROUND((E4/C4)*100,2) -> 91.25 | G4: {=_xlfn.IFS(F4>=90,"Premium",F4>=85,"Strong",F4<85,"Standard")} -> Premium | H4: =RANK(F4,$F$3:$F$17,0) -> 2
A5: Hunting Saddle | B5: 1 | C5: 840 | D5: 81 | E5: =ROUND(C5-D5,2) -> 759 | F5: =ROUND((E5/C5)*100,2) -> 90.36 | G5: {=_xlfn.IFS(F5>=90,"Premium",F5>=85,"Strong",F5<85,"Standard")} -> Premium | H5: =RANK(F5,$F$3:$F$17,0) -> 3
A6: Embossed Leather Portfolio | B6: 1 | C6: 350 | D6: 34 | E6: =ROUND(C6-D6,2) -> 316 | F6: =ROUND((E6/C6)*100,2) -> 90.29 | G6: {=_xlfn.IFS(F6>=90,"Premium",F6>=85,"Strong",F6<85,"Standard")} -> Premium | H6: =RANK(F6,$F$3:$F$17,0) -> 4
A7: Gentleman Riding Kit | B7: 1 | C7: 310 | D7: 34 | E7: =ROUND(C7-D7,2) -> 276 | F7: =ROUND((E7/C7)*100,2) -> 89.03 | G7: {=_xlfn.IFS(F7>=90,"Premium",F7>=85,"Strong",F7<85,"Standard")} -> Strong | H7: =RANK(F7,$F$3:$F$17,0) -> 5
A8: Full Dress Harness | B8: 1 | C8: 980 | D8: 113.5 | E8: =ROUND(C8-D8,2) -> 866.5 | F8: =ROUND((E8/C8)*100,2) -> 88.42 | G8: {=_xlfn.IFS(F8>=90,"Premium",F8>=85,"Strong",F8<85,"Standard")} -> Strong | H8: =RANK(F8,$F$3:$F$17,0) -> 6
A9: Bespoke Hunt Seat Saddle | B9: 1 | C9: 680 | D9: 81 | E9: =ROUND(C9-D9,2) -> 599 | F9: =ROUND((E9/C9)*100,2) -> 88.09 | G9: {=_xlfn.IFS(F9>=90,"Premium",F9>=85,"Strong",F9<85,"Standard")} -> Strong | H9: =RANK(F9,$F$3:$F$17,0) -> 7
A10: Ladies Riding Habit Set | B10: 1 | C10: 490 | D10: 60 | E10: =ROUND(C10-D10,2) -> 430 | F10: =ROUND((E10/C10)*100,2) -> 87.76 | G10: {=_xlfn.IFS(F10>=90,"Premium",F10>=85,"Strong",F10<85,"Standard")} -> Strong | H10: =RANK(F10,$F$3:$F$17,0) -> 8
A11: Hunting Bridle Set | B11: 1 | C11: 620 | D11: 77 | E11: =ROUND(C11-D11,2) -> 543 | F11: =ROUND((E11/C11)*100,2) -> 87.58 | G11: {=_xlfn.IFS(F11>=90,"Premium",F11>=85,"Strong",F11<85,"Standard")} -> Strong | H11: =RANK(F11,$F$3:$F$17,0) -> 9
A12: Royal Presentation Saddle | B12: 1 | C12: 1850 | D12: 264 | E12: =ROUND(C12-D12,2) -> 1586 | F12: =ROUND((E12/C12)*100,2) -> 85.73 | G12: {=_xlfn.IFS(F12>=90,"Premium",F12>=85,"Strong",F12<85,"Standard")} -> Strong | H12: =RANK(F12,$F$3:$F$17,0) -> 11
A13: Grand Parade Harness | B13: 1 | C13: 1340 | D13: 187 | E13: =ROUND(C13-D13,2) -> 1153 | F13: =ROUND((E13/C13)*100,2) -> 86.04 | G13: {=_xlfn.IFS(F13>=90,"Premium",F13>=85,"Strong",F13<85,"Standard")} -> Strong | H13: =RANK(F13,$F$3:$F$17,0) -> 10
A14: Officer Field Saddle | B14: 1 | C14: 720 | D14: 108.5 | E14: =ROUND(C14-D14,2) -> 611.5 | F14: =ROUND((E14/C14)*100,2) -> 84.93 | G14: {=_xlfn.IFS(F14>=90,"Premium",F14>=85,"Strong",F14<85,"Standard")} -> Standard | H14: =RANK(F14,$F$3:$F$17,0) -> 12
... A17: Silver Presentation Bridle | B17: 1 | C17: 920 | D17: 210.5 | E17: =ROUND(C17-D17,2) -> 709.5 | F17: =ROUND((E17/C17)*100,2) -> 77.12 | G17: {=_xlfn.IFS(F17>=90,"Premium",F17>=85,"Strong",F17<85,"Standard")} -> Standard | H17: =RANK(F17,$F$3:$F$17,0) -> 15

Sheet IV – Revenue & Growth
A2: Order Year | B2: Total Orders | C2: Annual Revenue (fr) | D2: Prev Year Revenue(fr) | E2: Cumulative Revenue (fr) | F2: YoY Growth % | G2: Era | H2: Sparkline
A3: 1838 | B3: 1 | C3: 980 | D3: =IF(ROW()=3,"",C2) | E3: =SUM($C$3:C3) -> 980 | F3: =IF(D3="","",ROUND(((C3-D3)/D3)*100,2)) | G3: {=_xlfn.IFS(AND(A3>=1837,A3<=1849),"Founding Decade",AND(A3>=1850,A3<=1859),"Consolidation",AND(A3>=1860,A3<=1869),"Expansion",AND(A3>=1870,A3<=1880),"Maturity")} -> Founding Decade
A4: 1840 | B4: 1 | C4: 1850 | D4: =IF(ROW()=3,"",C3) -> 980 | E4: =SUM($C$3:C4) -> 2830 | F4: =IF(D4="","",ROUND(((C4-D4)/D4)*100,2)) -> 88.78 | G4: {=_xlfn.IFS(AND(A4>=1837,A4<=1849),"Founding Decade",AND(A4>=1850,A4<=1859),"Consolidation",AND(A4>=1860,A4<=1869),"Expansion",AND(A4>=1870,A4<=1880),"Maturity")} -> Founding Decade
A5: 1842 | B5: 1 | C5: 620 | D5: =IF(ROW()=3,"",C4) -> 1850 | E5: =SUM($C$3:C5) -> 3450 | F5: =IF(D5="","",ROUND(((C5-D5)/D5)*100,2)) -> -66.49 | G5: {=_xlfn.IFS(AND(A5>=1837,A5<=1849),"Founding Decade",AND(A5>=1850,A5<=1859),"Consolidation",AND(A5>=1860,A5<=1869),"Expansion",AND(A5>=1870,A5<=1880),"Maturity")} -> Founding Decade
A6: 1843 | B6: 1 | C6: 540 | D6: =IF(ROW()=3,"",C5) -> 620 | E6: =SUM($C$3:C6) -> 3990 | F6: =IF(D6="","",ROUND(((C6-D6)/D6)*100,2)) -> -12.9 | G6: {=_xlfn.IFS(AND(A6>=1837,A6<=1849),"Founding Decade",AND(A6>=1850,A6<=1859),"Consolidation",AND(A6>=1860,A6<=1869),"Expansion",AND(A6>=1870,A6<=1880),"Maturity")} -> Founding Decade
A7: 1845 | B7: 1 | C7: 430 | D7: =IF(ROW()=3,"",C6) -> 540 | E7: =SUM($C$3:C7) -> 4420 | F7: =IF(D7="","",ROUND(((C7-D7)/D7)*100,2)) -> -20.37 | G7: {=_xlfn.IFS(AND(A7>=1837,A7<=1849),"Founding Decade",AND(A7>=1850,A7<=1859),"Consolidation",AND(A7>=1860,A7<=1869),"Expansion",AND(A7>=1870,A7<=1880),"Maturity")} -> Founding Decade
A8: 1847 | B8: 1 | C8: 1340 | D8: =IF(ROW()=3,"",C7) -> 430 | E8: =SUM($C$3:C8) -> 5760 | F8: =IF(D8="","",ROUND(((C8-D8)/D8)*100,2)) -> 211.63 | G8: {=_xlfn.IFS(AND(A8>=1837,A8<=1849),"Founding Decade",AND(A8>=1850,A8<=1859),"Consolidation",AND(A8>=1860,A8<=1869),"Expansion",AND(A8>=1870,A8<=1880),"Maturity")} -> Founding Decade
A9: 1848 | B9: 1 | C9: 840 | D9: =IF(ROW()=3,"",C8) -> 1340 | E9: =SUM($C$3:C9) -> 6600 | F9: =IF(D9="","",ROUND(((C9-D9)/D9)*100,2)) -> -37.31 | G9: {=_xlfn.IFS(AND(A9>=1837,A9<=1849),"Founding Decade",AND(A9>=1850,A9<=1859),"Consolidation",AND(A9>=1860,A9<=1869),"Expansion",AND(A9>=1870,A9<=1880),"Maturity")} -> Founding Decade
A10: 1849 | B10: 1 | C10: 1620 | D10: =IF(ROW()=3,"",C9) -> 840 | E10: =SUM($C$3:C10) -> 8220 | F10: =IF(D10="","",ROUND(((C10-D10)/D10)*100,2)) -> 92.86 | G10: {=_xlfn.IFS(AND(A10>=1837,A10<=1849),"Founding Decade",AND(A10>=1850,A10<=1859),"Consolidation",AND(A10>=1860,A10<=1869),"Expansion",AND(A10>=1870,A10<=1880),"Maturity")} -> Founding Decade
A11: 1851 | B11: 1 | C11: 720 | D11: =IF(ROW()=3,"",C10) -> 1620 | E11: =SUM($C$3:C11) -> 8940 | F11: =IF(D11="","",ROUND(((C11-D11)/D11)*100,2)) -> -55.56 | G11: {=_xlfn.IFS(AND(A11>=1837,A11<=1849),"Founding Decade",AND(A11>=1850,A11<=1859),"Consolidation",AND(A11>=1860,A11<=1869),"Expansion",AND(A11>=1870,A11<=1880),"Maturity")} -> Consolidation
A12: 1852 | B12: 1 | C12: 920 | D12: =IF(ROW()=3,"",C11) -> 720 | E12: =SUM($C$3:C12) -> 9860 | F12: =IF(D12="","",ROUND(((C12-D12)/D12)*100,2)) -> 27.78 | G12: {=_xlfn.IFS(AND(A12>=1837,A12<=1849),"Founding Decade",AND(A12>=1850,A12<=1859),"Consolidation",AND(A12>=1860,A12<=1869),"Expansion",AND(A12>=1870,A12<=1880),"Maturity")} -> Consolidation
A13: 1853 | B13: 1 | C13: 580 | D13: =IF(ROW()=3,"",C12) -> 920 | E13: =SUM($C$3:C13) -> 10440 | F13: =IF(D13="","",ROUND(((C13-D13)/D13)*100,2)) -> -36.96 | G13: {=_xlfn.IFS(AND(A13>=1837,A13<=1849),"Founding Decade",AND(A13>=1850,A13<=1859),"Consolidation",AND(A13>=1860,A13<=1869),"Expansion",AND(A13>=1870,A13<=1880),"Maturity")} -> Consolidation
A14: 1855 | B14: 1 | C14: 310 | D14: =IF(ROW()=3,"",C13) -> 580 | E14: =SUM($C$3:C14) -> 10750 | F14: =IF(D14="","",ROUND(((C14-D14)/D14)*100,2)) -> -46.55 | G14: {=_xlfn.IFS(AND(A14>=1837,A14<=1849),"Founding Decade",AND(A14>=1850,A14<=1859),"Consolidation",AND(A14>=1860,A14<=1869),"Expansion",AND(A14>=1870,A14<=1880),"Maturity")} -> Consolidation
... A31: 1879 | B31: 1 | C31: 320 | D31: =IF(ROW()=3,"",C30) -> 900 | E31: =SUM($C$3:C31) -> 31005 | F31: =IF(D31="","",ROUND(((C31-D31)/D31)*100,2)) -> -64.44 | G31: {=_xlfn.IFS(AND(A31>=1837,A31<=1849),"Founding Decade",AND(A31>=1850,A31<=1859),"Consolidation",AND(A31>=1860,A31<=1869),"Expansion",AND(A31>=1870,A31<=1880),"Maturity")} -> Maturity
